huaweicloudsdkcgs/__init__.py
huaweicloudsdkcgs/v5/__init__.py
huaweicloudsdkcgs/v5/cgs_async_client.py
huaweicloudsdkcgs/v5/cgs_client.py
huaweicloudsdkcgs/v5/model/__init__.py
huaweicloudsdkcgs/v5/model/container_node_info.py
huaweicloudsdkcgs/v5/model/list_container_nodes_request.py
huaweicloudsdkcgs/v5/model/list_container_nodes_response.py
huaweicloudsdkcgs/v5/region/__init__.py
huaweicloudsdkcgs/v5/region/cgs_region.py
huaweicloudsdkcgs-3.1.165.dist-info/LICENSE
huaweicloudsdkcgs-3.1.165.dist-info/METADATA
huaweicloudsdkcgs-3.1.165.dist-info/WHEEL
huaweicloudsdkcgs-3.1.165.dist-info/top_level.txt
huaweicloudsdkcgs-3.1.165.dist-info/RECORD
