Metadata-Version: 2.1
Name: huaweicloudsdkcgs
Version: 3.1.165
Summary: CGS
Home-page: https://github.com/huaweicloud/huaweicloud-sdk-python-v3
Author: HuaweiCloud SDK
Author-email: hwcloudsdk@huawei.com
License: Apache LICENSE 2.0
Keywords: huaweicloud,sdk,CGS
Classifier: Development Status :: 5 - Production/Stable
Classifier: Intended Audience :: Developers
Classifier: License :: OSI Approved :: Apache Software License
Classifier: Programming Language :: Python :: 3.6
Classifier: Programming Language :: Python :: 3.7
Classifier: Programming Language :: Python :: 3.8
Classifier: Programming Language :: Python :: 3.9
Classifier: Programming Language :: Python :: 3.10
Classifier: Programming Language :: Python :: 3.11
Classifier: Programming Language :: Python :: 3.12
Classifier: Topic :: Software Development
Requires-Python: >=3.6
License-File: LICENSE
Requires-Dist: huaweicloudsdkcore>=3.1.165
